README.rst
_description.org
lh-agpl3-LICENSE.txt
pyproject.toml
setup.py
bin/siteRegistrars-assemble.cs
bin/siteRegistrars-cbs-is-ds-sysd.cs
bin/siteRegistrars-roPerf-sysd.cs
bin/siteRegistrars-sbom.cs
bin/siteRegistrars-site-fps.cs
bin/svcInvSiteRegBox.cs
bin/svcInvSiteRegContainer.cs
bin/svcPerfSiteRegistrars.cs
bin/svcSiteRegBox.cs
bin/svcSiteRegContainer.cs
bin/svcSiteRegNets.cs
bin/svcSiteRegistrars.cs
bisos/__init__.py
bisos.siteRegistrars.egg-info/PKG-INFO
bisos.siteRegistrars.egg-info/SOURCES.txt
bisos.siteRegistrars.egg-info/dependency_links.txt
bisos.siteRegistrars.egg-info/not-zip-safe
bisos.siteRegistrars.egg-info/requires.txt
bisos.siteRegistrars.egg-info/top_level.txt
bisos/siteRegistrars/__init__.py
bisos/siteRegistrars/boxRegfps.py
bisos/siteRegistrars/containerRegfps.py
bisos/siteRegistrars/csSiteRegNets.py
bisos/siteRegistrars/invSiteRegBox.py
bisos/siteRegistrars/invSiteRegBoxConf.py
bisos/siteRegistrars/invSiteRegContainer.py
bisos/siteRegistrars/invSiteRegContainerConf.py
bisos/siteRegistrars/perfSap.py
bisos/siteRegistrars/perfSiteRegBox.py
bisos/siteRegistrars/perfSiteRegBoxConf.py
bisos/siteRegistrars/perfSiteRegContainer.py
bisos/siteRegistrars/perfSiteRegContainerConf.py
bisos/siteRegistrars/siteRegCurrentsLib.py
bisos/siteRegistrars/siteRegDaemonSysd.py
bisos/siteRegistrars/siteRegPkgThis.py