Metadata-Version: 2.2
Name: bisos.siteRegistrars
Version: 0.67
Summary: bisos.siteRegistrars:  CS Services for implementation of BISOS Site Regsitrars  -- box, cntnr and nets.
Author: Mohsen Banan
Author-email: libre@mohsen.1.banan.byname.net
Maintainer: Mohsen Banan
Maintainer-email: libre@mohsen.1.banan.byname.net
License: AGPL
Classifier: Development Status :: 5 - Production/Stable
Classifier: Intended Audience :: Developers
Classifier: License :: OSI Approved :: GNU Affero General Public License v3
Classifier: Operating System :: POSIX
Classifier: Programming Language :: Python
Classifier: Topic :: Software Development :: Libraries
Classifier: Topic :: Software Development :: Libraries :: Python Modules
Requires-Dist: bisos
Requires-Dist: bisos.b
Requires-Dist: bisos.banna
Requires-Dist: bisos.basics
Requires-Dist: bisos.bpo
Requires-Dist: bisos.capability
Requires-Dist: bisos.cntnr
Requires-Dist: bisos.common
Requires-Dist: bisos.csPlayer
Requires-Dist: bisos.currents
Requires-Dist: bisos.debian
Requires-Dist: bisos.marmee
Requires-Dist: bisos.platform
Requires-Dist: bisos.regfps
Requires-Dist: bisos.sbom
Requires-Dist: bisos.sites
Requires-Dist: setuptools==75.8.0
Dynamic: author
Dynamic: author-email
Dynamic: classifier
Dynamic: description
Dynamic: license
Dynamic: maintainer
Dynamic: maintainer-email
Dynamic: requires-dist
Dynamic: summary
